robopy/__init__.py
robopy/base/__init__.py
robopy/base/check_args.py
robopy/base/common.py
robopy/base/graphics.py
robopy/base/model.py
robopy/base/pose.py
robopy/base/quaternion.py
robopy/base/serial_link.py
robopy/base/super_pose.py
robopy/base/transforms.py
robopy/base/util.py
robopy/media/imgs/floor.jpg
robopy/media/imgs/logo_small.png
robopy/media/orion5/link0.stl
robopy/media/orion5/link1.stl
robopy/media/orion5/link2.stl
robopy/media/orion5/link3.stl
robopy/media/orion5/link4.stl
robopy/media/orion5/link5.stl
robopy/media/orion5/link6.stl
robopy/media/puma_560/link0.stl
robopy/media/puma_560/link1.stl
robopy/media/puma_560/link2.stl
robopy/media/puma_560/link3.stl
robopy/media/puma_560/link4.stl
robopy/media/puma_560/link5.stl
robopy/media/puma_560/link6.stl
robopy/tests/__init__.py
robopy/tests/test_common.py
robopy/tests/test_pose.py
robopy/tests/test_transforms.py
robopy-1.0.8.dist-info/METADATA
robopy-1.0.8.dist-info/RECORD
robopy-1.0.8.dist-info/WHEEL
robopy-1.0.8.dist-info/top_level.txt
